lsyflasksdkcore/__init__.py
lsyflasksdkcore/blueprints.py
lsyflasksdkcore/context.py
lsyflasksdkcore/excel.py
lsyflasksdkcore/exceptions.py
lsyflasksdkcore/model.py
lsyflasksdkcore/schema.py
lsyflasksdkcore/serialization.py
lsyflasksdkcore/decorators/__init__.py
lsyflasksdkcore/export/__init__.py
lsyflasksdkcore/export/cvs.py
lsyflasksdkcore/export/xls.py
lsyflasksdkcore/linq/__init__.py
lsyflasksdkcore/linq/core.py
lsyflasksdkcore/linq/linq_exceptions.py
lsyflasksdkcore/logging/__init__.py
lsyflasksdkcore/logging/file_logger.py
lsyflasksdkcore/logging/stash_logger.py
lsyflasksdkcore/swagger/__init__.py
lsyflasksdkcore/swagger/doc.py
lsyflasksdkcore/swagger/plugins.py
lsyflasksdkcore/swagger/test.py
lsyflasksdkcore/utils/__init__.py
lsyflasksdkcore/utils/jwt.py
lsyflasksdkcore/utils/lazy.py
lsyflasksdkcore/utils/tree.py
lsyflasksdkcore/utils/unique.py
lsyflasksdkcore-1.0.4.dist-info/METADATA
lsyflasksdkcore-1.0.4.dist-info/WHEEL
lsyflasksdkcore-1.0.4.dist-info/top_level.txt
lsyflasksdkcore-1.0.4.dist-info/RECORD
