Metadata-Version: 2.1
Name: lsyflasksdkcore
Version: 1.0.4
Summary: lsyflasksdkcore
Home-page: https://gitee.com/linkeddt/lsyflasksdkcore.git
Author: fhp
Author-email: chinafengheping@outlook.com
License: UNKNOWN
Platform: UNKNOWN
Requires-Dist: apispec (==4.4.0)
Requires-Dist: apispec-webframeworks (==0.5.2)
Requires-Dist: click (==8.1.3)
Requires-Dist: colorama (==0.4.4)
Requires-Dist: Flask (==1.1.2)
Requires-Dist: Flask-Login (==0.5.0)
Requires-Dist: itsdangerous (==2.0.1)
Requires-Dist: Jinja2 (==3.0.2)
Requires-Dist: MarkupSafe (==2.1.1)
Requires-Dist: marshmallow (==3.11.1)
Requires-Dist: PyJWT (==2.1.0)
Requires-Dist: python-logstash (==0.4.6)
Requires-Dist: PyYAML (==6.0)
Requires-Dist: six (==1.16.0)
Requires-Dist: swagger-ui-py (==0.3.0)
Requires-Dist: Werkzeug (==2.0.2)
Requires-Dist: xlrd (==1.2.0)
Requires-Dist: xlutils (==2.0.0)
Requires-Dist: xlwt (==1.3.0)
